comandante/__init__.py
comandante/decorators.py
comandante/errors.py
comandante/handler.py
comandante/types.py
comandante/inner/__init__.py
comandante/inner/bind.py
comandante/inner/helpers.py
comandante/inner/model.py
comandante/inner/parser.py
comandante/inner/proxy.py
comandante/inner/test.py
comandante/inner/output/__init__.py
comandante/inner/output/help_writer.py
comandante/inner/output/markup.py
comandante/inner/output/terminal.py
comandante/inner/output/token_processor.py
comandante-0.0.3.dist-info/LICENSE
comandante-0.0.3.dist-info/LICENSE.md
comandante-0.0.3.dist-info/METADATA
comandante-0.0.3.dist-info/WHEEL
comandante-0.0.3.dist-info/top_level.txt
comandante-0.0.3.dist-info/RECORD
